<?xml version="1.0" encoding="UTF-8"?>
<category_tree>
<category>
  <id>0</id>
  <name>All Items</name>
  <pid>0</pid>
</category>
<category>
  <id>1</id>
  <name>Home &amp; Office</name>
  <pid>0</pid>
</category>
<category>
  <id>6</id>
  <name>Home Improvement</name>
  <pid>1</pid>
</category>
<category>
  <id>7</id>
  <name>Lawn &amp; Garden</name>
  <pid>1</pid>
</category>
<category>
  <id>2</id>
  <name>Sports &amp; Outdoors</name>
  <pid>0</pid>
</category>
<category>
  <id>8</id>
  <name>Sports Equipment</name>
  <pid>2</pid>
</category>
<category>
  <id>17</id>
  <name>Golf</name>
  <pid>8</pid>
</category>
<category>
  <id>18</id>
  <name>Curling</name>
  <pid>8</pid>
</category>
<category>
  <id>19</id>
  <name>Curling Stones</name>
  <pid>18</pid>
</category>
<category>
  <id>9</id>
  <name>Camping Gear</name>
  <pid>2</pid>
</category>
<category>
  <id>3</id>
  <name>Electronics</name>
  <pid>0</pid>
</category>
<category>
  <id>10</id>
  <name>Computers</name>
  <pid>3</pid>
</category>
<category>
  <id>15</id>
  <name>Laptops</name>
  <pid>10</pid>
</category>
<category>
  <id>16</id>
  <name>Desktops</name>
  <pid>10</pid>
</category>
<category>
  <id>11</id>
  <name>MP3 Players</name>
  <pid>3</pid>
</category>
<category>
  <id>12</id>
  <name>Tablets</name>
  <pid>3</pid>
</category>
<category>
  <id>20</id>
  <name>Video Games</name>
  <pid>3</pid>
</category>
<category>
  <id>21</id>
  <name>Appliances</name>
  <pid>3</pid>
</category>
<category>
  <id>4</id>
  <name>Clothing</name>
  <pid>0</pid>
</category>
<category>
  <id>13</id>
  <name>Shoes</name>
  <pid>4</pid>
</category>
<category>
  <id>14</id>
  <name>Formal Wear</name>
  <pid>4</pid>
</category>
<category>
  <id>5</id>
  <name>Books</name>
  <pid>0</pid>
</category>
<category>
  <id>22</id>
  <name>Pet Care</name>
  <pid>0</pid>
</category>
<category>
  <id>23</id>
  <name>Food &amp; Drink</name>
  <pid>0</pid>
</category>
<category>
  <id>24</id>
  <name>Beverages</name>
  <pid>23</pid>
</category>
<category>
  <id>26</id>
  <name>Alcoholic Beverages</name>
  <pid>24</pid>
</category>
<category>
  <id>25</id>
  <name>Food</name>
  <pid>23</pid>
</category>
</category_tree>
